Metadata-Version: 1.0
Name: deepak
Version: 0.0.11
Summary: test Installation Module
Home-page: http://github.com/sunlove123
Author: DeenaDhayalan
Author-email: deenadhayalan.b.cts@gmail.com
License: MIT
Platform: UNKNOWN
